filtersam/__init__.py
filtersam/cli.py
filtersam/filtersam.py
filtersam/utils.py
filtersam-0.0.11.dist-info/LICENSE
filtersam-0.0.11.dist-info/METADATA
filtersam-0.0.11.dist-info/WHEEL
filtersam-0.0.11.dist-info/entry_points.txt
filtersam-0.0.11.dist-info/top_level.txt
filtersam-0.0.11.dist-info/RECORD
