Metadata-Version: 2.1
Name: filtersam
Version: 0.0.11
Summary: ('Tools to filter sam o bam files by percent identity or percent of matched sequence',)
Home-page: http://github.com/robaina/filterSAM
Author: Semidán Robaina Estévez, 2021-2022
Author-email: srobaina@ull.edu.es
Maintainer: Semidán Robaina Estévez
Maintainer-email: srobaina@gmail.com
License: Creative Commons Attribution 4.0 International
Download-URL: http://github.com/robaina/filterSAM
Platform: UNKNOWN
License-File: LICENSE
Requires-Dist: numpy
Requires-Dist: pysam
Requires-Dist: parallelbam
